ks_st
