Metadata-Version: 2.1
Name: ks-st
Version: 0.0.9
Summary: Style transfer toolbox
Home-page: https://github.com/Armandpl/ks_st
Author: Armandpl
Author-email: adpl33@gmail.com
License: UNKNOWN
Platform: UNKNOWN
Classifier: Programming Language :: Python :: 3
Classifier: License :: OSI Approved :: MIT License
Classifier: Operating System :: OS Independent
Requires-Python: >=3.6
